quote_lines/__init__.py
quote_lines/py.typed
quote_lines/quote.py
quote_lines-1.3.1.dist-info/LICENSE
quote_lines-1.3.1.dist-info/METADATA
quote_lines-1.3.1.dist-info/WHEEL
quote_lines-1.3.1.dist-info/entry_points.txt
quote_lines-1.3.1.dist-info/top_level.txt
quote_lines-1.3.1.dist-info/RECORD
