Metadata-Version: 2.1
Name: quote_lines
Version: 1.3.1
Summary: A tiny CLI used for quoting input lines
License: GPL
Project-URL: Homepage, https://github.com/zwimer/quote
Classifier: Programming Language :: Python :: 3
Classifier: Programming Language :: Python :: 3.10
Requires-Python: >=3.10
License-File: LICENSE
